Metadata-Version: 2.1
Name: odoo14-addon-stock_warehouse_flow
Version: 14.0.2.1.1
Summary: Configure routing flow for stock moves
Home-page: https://github.com/OCA/wms
Author: Camptocamp, BCIM, Odoo Community Association (OCA)
Author-email: support@odoo-community.org
License: AGPL-3
Classifier: Programming Language :: Python
Classifier: Framework :: Odoo
Classifier: Framework :: Odoo :: 14.0
Classifier: License :: OSI Approved :: GNU Affero General Public License v3
Classifier: Development Status :: 3 - Alpha
Requires-Python: >=3.6
Requires-Dist: odoo14-addon-delivery-procurement-group-carrier
Requires-Dist: odoo<14.1dev,>=14.0a
